SpatialCluster/__init__.py
SpatialCluster/constants.py
SpatialCluster/datasets.py
SpatialCluster/data/reduced_data_MinMaxScaler_PCA_manzana_224.csv
SpatialCluster/methods/DMoN.py
SpatialCluster/methods/DMoN_core.py
SpatialCluster/methods/GMM.py
SpatialCluster/methods/KNN.py
SpatialCluster/methods/SOM.py
SpatialCluster/methods/TDI.py
SpatialCluster/methods/__init__.py
SpatialCluster/metrics/AMI.py
SpatialCluster/metrics/ARI.py
SpatialCluster/metrics/__init__.py
SpatialCluster/preprocess/__init__.py
SpatialCluster/preprocess/adjacency.py
SpatialCluster/preprocess/data_format.py
SpatialCluster/preprocess/rings.py
SpatialCluster/utils/__init__.py
SpatialCluster/utils/data_format.py
SpatialCluster/utils/data_structures.py
SpatialCluster/utils/get_areas.py
SpatialCluster/visualization/__init__.py
SpatialCluster/visualization/plotters.py
SpatialCluster-1.0.0.dist-info/LICENSE
SpatialCluster-1.0.0.dist-info/METADATA
SpatialCluster-1.0.0.dist-info/WHEEL
SpatialCluster-1.0.0.dist-info/top_level.txt
SpatialCluster-1.0.0.dist-info/RECORD
