Metadata-Version: 2.1
Name: SpatialCluster
Version: 1.0.0
Summary: Spatial cluster package
Home-page: https://github.com/AxlKings/SpatialCluster
Author: AxelReyesO (Axel Reyes O)
Author-email: <axel.reyes@sansano.usm.cl>
License: MIT
Keywords: python spatial urban cluster
Classifier: Development Status :: 1 - Planning
Classifier: Intended Audience :: Developers
Classifier: Programming Language :: Python :: 3
Classifier: Operating System :: Unix
Classifier: Operating System :: MacOS :: MacOS X
Classifier: Operating System :: Microsoft :: Windows
License-File: LICENSE
Requires-Dist: scikit-learn
Requires-Dist: tensorflow
Requires-Dist: scipy
Requires-Dist: numpy
Requires-Dist: matplotlib
Requires-Dist: folium
Requires-Dist: minisom
Requires-Dist: seaborn
Requires-Dist: geopandas
Requires-Dist: contextily
